<?xml version="1.0" encoding="iso-8859-1"?>
<binding type="db" autogen="true"><table>APPUNTAMENTI__PRENOTAZIONE</table><bind element="persona" dbField="PERSONA"/><bind element="utente" dbField="UTENTE"/><bind element="operatore" dbField="ID_OPERATORE"/><bind element="tipo" dbField="ID_TIPO"/><bind element="email" dbField="EMAIL"/><bind element="telefono" dbField="TELEFONO"/><bind element="inizio" dbField="INIZIO"/><bind element="fine" dbField="FINE"/><bind element="note" dbField="NOTE"/><bind element="noteUfficio" dbField="NOTEUFFICIO"/><bind element="motivoAnnullamento" dbField="MOTIVOANNULLAMENTO"/><bind element="nrIstanza" dbField="NRISTANZA"/><bind element="stato" dbField="ID_STATO"/><bind element="allegato" dbField="ALLEGATO"/></binding>
